odoo/addons/l10n_es_aeat_mod369/README.rst
odoo/addons/l10n_es_aeat_mod369/__init__.py
odoo/addons/l10n_es_aeat_mod369/__manifest__.py
odoo/addons/l10n_es_aeat_mod369/data/tax_code_map_mod369_data.xml
odoo/addons/l10n_es_aeat_mod369/data/2022/aeat.model.export.config.csv
odoo/addons/l10n_es_aeat_mod369/data/2022/l10n.es.aeat.map.tax.line.csv
odoo/addons/l10n_es_aeat_mod369/data/2022/00/aeat.model.export.config.line.csv
odoo/addons/l10n_es_aeat_mod369/data/2022/04/aeat.model.export.config.line.csv
odoo/addons/l10n_es_aeat_mod369/data/2022/05/aeat.model.export.config.line.csv
odoo/addons/l10n_es_aeat_mod369/data/2022/06/aeat.model.export.config.line.csv
odoo/addons/l10n_es_aeat_mod369/data/2022/07/aeat.model.export.config.line.csv
odoo/addons/l10n_es_aeat_mod369/data/2022/08/aeat.model.export.config.line.csv
odoo/addons/l10n_es_aeat_mod369/data/2022/09/aeat.model.export.config.line.csv
odoo/addons/l10n_es_aeat_mod369/data/2022/main/aeat.model.export.config.line.csv
odoo/addons/l10n_es_aeat_mod369/docs/DR369e21.xlsx
odoo/addons/l10n_es_aeat_mod369/docs/Descripcion_PresentacionFichero369_v1.pdf
odoo/addons/l10n_es_aeat_mod369/i18n/es.po
odoo/addons/l10n_es_aeat_mod369/i18n/l10n_es_aeat_mod369.pot
odoo/addons/l10n_es_aeat_mod369/models/__init__.py
odoo/addons/l10n_es_aeat_mod369/models/account_tax.py
odoo/addons/l10n_es_aeat_mod369/models/l10n_es_aeat_map_tax_line.py
odoo/addons/l10n_es_aeat_mod369/models/l10n_es_aeat_tax_line.py
odoo/addons/l10n_es_aeat_mod369/models/mod369.py
odoo/addons/l10n_es_aeat_mod369/models/mod369_line.py
odoo/addons/l10n_es_aeat_mod369/models/mod369_line_grouped.py
odoo/addons/l10n_es_aeat_mod369/readme/CONTRIBUTORS.md
odoo/addons/l10n_es_aeat_mod369/readme/DESCRIPTION.md
odoo/addons/l10n_es_aeat_mod369/readme/ROADMAP.md
odoo/addons/l10n_es_aeat_mod369/readme/USAGE.md
odoo/addons/l10n_es_aeat_mod369/security/ir.model.access.csv
odoo/addons/l10n_es_aeat_mod369/security/l10n_es_aeat_mod369_security.xml
odoo_addon_l10n_es_aeat_mod369-18.0.1.0.1.dist-info/METADATA
odoo_addon_l10n_es_aeat_mod369-18.0.1.0.1.dist-info/WHEEL
odoo_addon_l10n_es_aeat_mod369-18.0.1.0.1.dist-info/top_level.txt
odoo_addon_l10n_es_aeat_mod369-18.0.1.0.1.dist-info/RECORD
